<?xml version="1.0" encoding="UTF-8"?>
<databaseChangeLog
        xmlns="http://www.liquibase.org/xml/ns/dbchangelog"
        xmlns:pro="http://www.liquibase.org/xml/ns/pro"
        xmlns:xsi="http://www.w3.org/2001/XMLSchema-instance"
        xsi:schemaLocation="
          http://www.liquibase.org/xml/ns/dbchangelog
          http://www.liquibase.org/xml/ns/dbchangelog/dbchangelog-latest.xsd
          http://www.liquibase.org/xml/ns/pro
          http://www.liquibase.org/xml/ns/pro/liquibase-pro-latest.xsd">
    <include file="./tables/types.sql" relativeToChangelogFile="true" />
    <include file="./functions/fn_set_updated_at.sql" relativeToChangelogFile="true" />
    <include file="./functions/fn_log_status_change.sql" relativeToChangelogFile="true" />
    <include file="./tables/companies.sql" relativeToChangelogFile="true" />
    <include file="./tables/users.sql" relativeToChangelogFile="true" />
    <include file="./tables/offices.sql" relativeToChangelogFile="true" />
    <include file="./tables/shipments.sql" relativeToChangelogFile="true" />
    <include file="./tables/shipment_status_history.sql" relativeToChangelogFile="true" />
    <include file="./triggers/trg_set_updated_at.sql" relativeToChangelogFile="true" />
    <include file="./triggers/trg_shipment_history_audit.sql" relativeToChangelogFile="true" />
    <include file="./demo_data/01_initial_demo_data.sql" relativeToChangelogFile="true" />
</databaseChangeLog>
